hubspot_webhook_model/__init__.py
hubspot_webhook_model/py.typed
hubspot_webhook_model-0.2.0.dist-info/METADATA
hubspot_webhook_model-0.2.0.dist-info/WHEEL
hubspot_webhook_model-0.2.0.dist-info/RECORD
